{"uid":"org.graalvm.java","name":"GraalVM Java","formatVersion":1,"version":"java17","releaseTime":"2023-06-13T07:50:15.000Z","runtimes":[{"name":"oracle_graalvm_jdk17.0.9","runtimeOS":"windows-x64","version":{"major":17,"minor":0,"security":9},"releaseTime":"2023-10-24T10:31:36.000Z","vendor":"oracle","packageType":"jdk","downloadType":"archive","checksum":{"type":"sha256","hash":"285e045bfc0b87d2b61958fea97444c3c6c7e68fba3fdbbe146622328b52ec38"},"url":"https://github.com/graalvm/graalvm-ce-builds/releases/download/jdk-17.0.9/graalvm-community-jdk-17.0.9_windows-x64_bin.zip"},{"name":"oracle_graalvm_jdk17.0.9","runtimeOS":"linux-x64","version":{"major":17,"minor":0,"security":9},"releaseTime":"2023-10-24T10:31:15.000Z","vendor":"oracle","packageType":"jdk","downloadType":"archive","checksum":{"type":"sha256","hash":"e47ba7229cef02393e19d5b8f46f7f1cab4829dd17bfe84d5431fc8ff0e22a96"},"url":"https://github.com/graalvm/graalvm-ce-builds/releases/download/jdk-17.0.9/graalvm-community-jdk-17.0.9_linux-x64_bin.tar.gz"},{"name":"oracle_graalvm_jdk17.0.9","runtimeOS":"linux-arm64","version":{"major":17,"minor":0,"security":9},"releaseTime":"2023-10-24T10:30:48.000Z","vendor":"oracle","packageType":"jdk","downloadType":"archive","checksum":{"type":"sha256","hash":"c3281b21f5220c2f76cf6fa0d646bc42e2d729af2c022bb06e557a613ba16102"},"url":"https://github.com/graalvm/graalvm-ce-builds/releases/download/jdk-17.0.9/graalvm-community-jdk-17.0.9_linux-aarch64_bin.tar.gz"},{"name":"oracle_graalvm_jdk17.0.9","runtimeOS":"mac-os-x64","version":{"major":17,"minor":0,"security":9},"releaseTime":"2023-10-24T10:30:26.000Z","vendor":"oracle","packageType":"jdk","downloadType":"archive","checksum":{"type":"sha256","hash":"543dd286d99c04788847ef6366f794c059a69e77added577916186371e206e33"},"url":"https://github.com/graalvm/graalvm-ce-builds/releases/download/jdk-17.0.9/graalvm-community-jdk-17.0.9_macos-x64_bin.tar.gz"},{"name":"oracle_graalvm_jdk17.0.9","runtimeOS":"mac-os-arm64","version":{"major":17,"minor":0,"security":9},"releaseTime":"2023-10-24T10:30:05.000Z","vendor":"oracle","packageType":"jdk","downloadType":"archive","checksum":{"type":"sha256","hash":"3eccc4ffda01818172b7fc7cdf4379bc62ed7129ee30ca854c04da67057249c9"},"url":"https://github.com/graalvm/graalvm-ce-builds/releases/download/jdk-17.0.9/graalvm-community-jdk-17.0.9_macos-aarch64_bin.tar.gz"},{"name":"oracle_graalvm_jdk17.0.8","runtimeOS":"windows-x64","version":{"major":17,"minor":0,"security":8},"releaseTime":"2023-07-23T17:18:31.000Z","vendor":"oracle","packageType":"jdk","downloadType":"archive","checksum":{"type":"sha256","hash":"31e60e416b015057a7826fa489ac9753261e815a525fa362f8a770a3d0a364b0"},"url":"https://github.com/graalvm/graalvm-ce-builds/releases/download/jdk-17.0.8/graalvm-community-jdk-17.0.8_windows-x64_bin.zip"},{"name":"oracle_graalvm_jdk17.0.8","runtimeOS":"linux-x64","version":{"major":17,"minor":0,"security":8},"releaseTime":"2023-07-23T17:18:12.000Z","vendor":"oracle","packageType":"jdk","downloadType":"archive","checksum":{"type":"sha256","hash":"1dffdf5c7cc5bf38558e9f093eef6a14072a6dff0be3a9906208b37b53ecc009"},"url":"https://github.com/graalvm/graalvm-ce-builds/releases/download/jdk-17.0.8/graalvm-community-jdk-17.0.8_linux-x64_bin.tar.gz"},{"name":"oracle_graalvm_jdk17.0.8","runtimeOS":"linux-arm64","version":{"major":17,"minor":0,"security":8},"releaseTime":"2023-07-23T17:17:54.000Z","vendor":"oracle","packageType":"jdk","downloadType":"archive","checksum":{"type":"sha256","hash":"c4f26318114d6bd125cc95ee070289afdd42c6683867adf832f2ab2819c3b685"},"url":"https://github.com/graalvm/graalvm-ce-builds/releases/download/jdk-17.0.8/graalvm-community-jdk-17.0.8_linux-aarch64_bin.tar.gz"},{"name":"oracle_graalvm_jdk17.0.8","runtimeOS":"mac-os-x64","version":{"major":17,"minor":0,"security":8},"releaseTime":"2023-07-23T17:17:37.000Z","vendor":"oracle","packageType":"jdk","downloadType":"archive","checksum":{"type":"sha256","hash":"cf4bb646018da8bf93f67e5cdae0f583b276d278d0b667d779a68d11d3b6873d"},"url":"https://github.com/graalvm/graalvm-ce-builds/releases/download/jdk-17.0.8/graalvm-community-jdk-17.0.8_macos-x64_bin.tar.gz"},{"name":"oracle_graalvm_jdk17.0.8","runtimeOS":"mac-os-arm64","version":{"major":17,"minor":0,"security":8},"releaseTime":"2023-07-23T17:17:19.000Z","vendor":"oracle","packageType":"jdk","downloadType":"archive","checksum":{"type":"sha256","hash":"89209bbf8346d8dd0847d431bd8654db7d4ff634745207f20af2045c4869fb49"},"url":"https://github.com/graalvm/graalvm-ce-builds/releases/download/jdk-17.0.8/graalvm-community-jdk-17.0.8_macos-aarch64_bin.tar.gz"},{"name":"oracle_graalvm_jdk17.0.7","runtimeOS":"windows-x64","version":{"major":17,"minor":0,"security":7},"releaseTime":"2023-06-13T07:51:41.000Z","vendor":"oracle","packageType":"jdk","downloadType":"archive","checksum":{"type":"sha256","hash":"1fa8d5f56e7d2bbc3033e7f1f562d9ff0d07431436ca7d781c40c5433eedd348"},"url":"https://github.com/graalvm/graalvm-ce-builds/releases/download/jdk-17.0.7/graalvm-community-jdk-17.0.7_windows-x64_bin.zip"},{"name":"oracle_graalvm_jdk17.0.7","runtimeOS":"linux-x64","version":{"major":17,"minor":0,"security":7},"releaseTime":"2023-06-13T07:51:22.000Z","vendor":"oracle","packageType":"jdk","downloadType":"archive","checksum":{"type":"sha256","hash":"094e5a7dcc4a903b70741d5c3c1688f83e83e2d44eb3d8d798c5d79ed902032c"},"url":"https://github.com/graalvm/graalvm-ce-builds/releases/download/jdk-17.0.7/graalvm-community-jdk-17.0.7_linux-x64_bin.tar.gz"},{"name":"oracle_graalvm_jdk17.0.7","runtimeOS":"linux-arm64","version":{"major":17,"minor":0,"security":7},"releaseTime":"2023-06-13T07:51:05.000Z","vendor":"oracle","packageType":"jdk","downloadType":"archive","checksum":{"type":"sha256","hash":"cb5bedf6244d30018856559a393029e98de48c9608eb35ec6c4937dcb7d97224"},"url":"https://github.com/graalvm/graalvm-ce-builds/releases/download/jdk-17.0.7/graalvm-community-jdk-17.0.7_linux-aarch64_bin.tar.gz"},{"name":"oracle_graalvm_jdk17.0.7","runtimeOS":"mac-os-x64","version":{"major":17,"minor":0,"security":7},"releaseTime":"2023-06-13T07:50:46.000Z","vendor":"oracle","packageType":"jdk","downloadType":"archive","checksum":{"type":"sha256","hash":"7b38776fc9259af5b9b02ffa21d8c7bf3991fa29bc689d6d1a10a305cd8f50af"},"url":"https://github.com/graalvm/graalvm-ce-builds/releases/download/jdk-17.0.7/graalvm-community-jdk-17.0.7_macos-x64_bin.tar.gz"},{"name":"oracle_graalvm_jdk17.0.7","runtimeOS":"mac-os-arm64","version":{"major":17,"minor":0,"security":7},"releaseTime":"2023-06-13T07:50:15.000Z","vendor":"oracle","packageType":"jdk","downloadType":"archive","checksum":{"type":"sha256","hash":"05d9a51786c578cea346760b3ec3af3721780afb850b739407a2a123f5d081fd"},"url":"https://github.com/graalvm/graalvm-ce-builds/releases/download/jdk-17.0.7/graalvm-community-jdk-17.0.7_macos-aarch64_bin.tar.gz"}]}